tck/GMM_MAP_EM.py
tck/GMMposterior.py
tck/TCK.py
tck/__init__.py
tck/datasets.py
tck-1.0.0.dist-info/LICENSE
tck-1.0.0.dist-info/METADATA
tck-1.0.0.dist-info/WHEEL
tck-1.0.0.dist-info/top_level.txt
tck-1.0.0.dist-info/RECORD
