Metadata-Version: 2.1
Name: tck
Version: 1.0.0
Summary: Kernel similarity for classification and clustering of multi-variate time series with missing values.
Home-page: https://github.com/FilippoMB/Time-Series-Cluster-Kernel
Author: Filippo Maria Bianchi
Author-email: filippombianchi@gmail.com
Classifier: Programming Language :: Python :: 3
Classifier: License :: OSI Approved :: MIT License
Classifier: Operating System :: OS Independent
Requires-Python: >=3.9
License-File: LICENSE
Requires-Dist: numpy >1.19.5
Requires-Dist: scikit-learn >=1.4
Requires-Dist: scipy
Requires-Dist: requests
Requires-Dist: tqdm
